[
  {
    "fecha": "3/6/2026",
    "emision": "005582",
    "revista": "03_005582_RUEDA DE ORO_TI5RHB_HORA UTC:22 A 23:15_FRECUENCIA 7130 MHZ_TI3OMY",
    "operador": "TI2GC",
    "nombreOp": "GUILLERMO",
    "totalEstaciones": 21,
    "duracion": "1h 27min",
    "tempProm": "19.6",
    "masLejano": {
      "indicativo": "OA4DQV",
      "nombre": "EDGAR QUISPE CCOSCCO",
      "dist": 2586,
      "grilla": "FH18LB"
    },
    "zonaActiva": [
      "EK70",
      6
    ],
    "timestamp": "2026-06-03T23:26:18.077Z"
  },
  {
    "fecha": "2/6/2026",
    "emision": "005581",
    "revista": "02_005581_RUEDA DE ORO_TI5RHB_HORA UTC:22 A 23:15_FRECUENCIA 7130 MHZ_TI3OMY",
    "operador": "TI2GC",
    "nombreOp": "GUILLERMO",
    "totalEstaciones": 19,
    "duracion": "2h 59min",
    "tempProm": "22.3",
    "masLejano": {
      "indicativo": "CM8SS",
      "nombre": "JOSE LUIS FERNANDEZ",
      "dist": 1424,
      "grilla": "EL92ET"
    },
    "zonaActiva": [
      "EK70",
      4
    ],
    "timestamp": "2026-06-03T00:59:11.672Z"
  },
  {
    "fecha": "1/6/2026",
    "emision": "5580",
    "revista": "01_005580_RUEDA DE ORO_TI5RHB_HORA UTC:22 A 23:15_FRECUENCIA 7130 MHZ_TI3OMY",
    "operador": "TI2GC",
    "nombreOp": "GUILLERMO",
    "totalEstaciones": 13,
    "duracion": "1h 32min",
    "tempProm": "21.1",
    "masLejano": {
      "indicativo": "CM8SS",
      "nombre": "JOSE LUIS FERNANDEZ",
      "dist": 1424,
      "grilla": "EL92ET"
    },
    "zonaActiva": [
      "EJ89",
      5
    ],
    "timestamp": "2026-06-01T23:32:29.191Z"
  },
  {
    "fecha": "31/5/2026",
    "emision": "009646",
    "revista": "31_009646_RUEDA DE ORO_TI5RHB_HORA UTC:22 A 23:15_FRECUENCIA 7130 MHZ_TI3OMY",
    "operador": "TI2GC",
    "nombreOp": "GUILLERMO",
    "totalEstaciones": 17,
    "duracion": "1h 25min",
    "tempProm": "22.2",
    "masLejano": {
      "indicativo": "CM8SS",
      "nombre": "JOSE LUIS FERNANDEZ",
      "dist": 1424,
      "grilla": "EL92ET"
    },
    "zonaActiva": [
      "EK70",
      5
    ],
    "timestamp": "2026-05-31T23:29:25.997Z"
  },
  {
    "fecha": "27/5/2026",
    "emision": "009641",
    "revista": "009641_RUEDA DE ORO_TI5RHB_ HORA UTC 22 A 23:15_Frecuencia 7130 MHZ-_TI3OMY_26/05/2026",
    "operador": "TI2GC",
    "nombreOp": "GUILLERMO",
    "totalEstaciones": 26,
    "duracion": "11min 31s",
    "tempProm": "19.5",
    "masLejano": {
      "indicativo": "CM8SS",
      "nombre": "JOSE LUIS FERNANDEZ",
      "dist": 1424,
      "grilla": "EL92ET"
    },
    "zonaActiva": [
      "EK70",
      8
    ],
    "timestamp": "2026-05-28T04:06:26.554Z"
  },
  {
    "fecha": "25/5/2026",
    "emision": "009640",
    "revista": "009640_RUEDA DE ORO_TI5RHB_HORA UTC:22 A 23:15_FRECUENCIA 7130 MHZ_TI3OMY",
    "operador": "TI2GC",
    "nombreOp": "GUILLERMO",
    "totalEstaciones": 23,
    "duracion": "54min 13s",
    "tempProm": "21.6",
    "masLejano": {
      "indicativo": "CM8SS",
      "nombre": "JOSE LUIS FERNANDEZ",
      "dist": 1424,
      "grilla": "EL92ET"
    },
    "zonaActiva": [
      "EK70",
      6
    ],
    "timestamp": "2026-05-25T23:30:15.445Z"
  },
  {
    "fecha": "25/5/2026",
    "emision": "009639",
    "revista": "009639_RUEDA DE ORO_TI5RHB_ HORA UTC 22 A 23:15_Frecuencia 7130 MHZ-_TI3OMY",
    "operador": "TI2GC",
    "nombreOp": "GUILLERMO",
    "totalEstaciones": 20,
    "duracion": "13min 45s",
    "tempProm": "24.5",
    "masLejano": {
      "indicativo": "CM8SS",
      "nombre": "JOSE LUIS",
      "dist": 1424,
      "grilla": "EL92ET"
    },
    "zonaActiva": [
      "EK70",
      5
    ],
    "timestamp": "2026-05-25T20:58:20.444Z"
  },
  {
    "fecha": "24/5/2026",
    "emision": "009638",
    "revista": "009638_RUEDA DE ORO_TI5RHB_ HORA UTC 22 A 23:15_Frecuencia 7130 MHZ-_TI3OMY",
    "operador": "TI2GC",
    "nombreOp": "GUILLERMO",
    "totalEstaciones": 17,
    "duracion": "11min 41s",
    "tempProm": "20.2",
    "masLejano": {
      "indicativo": "HI8GAG",
      "nombre": "GUSTAVO",
      "dist": 1761,
      "grilla": "FK48WK"
    },
    "zonaActiva": [
      "EK70",
      5
    ],
    "timestamp": "2026-05-25T03:03:26.373Z"
  },
  {
    "fecha": "22/5/2026",
    "emision": "009637",
    "revista": "009637_RUEDA DE ORO_TI5RHB_HORA UTC:22 A 23:15_FRECUENCIA 7130 MHZ",
    "operador": "TI2GC",
    "nombreOp": "GUILLERMO",
    "totalEstaciones": 21,
    "duracion": "1h 14min",
    "tempProm": "20.3",
    "masLejano": {
      "indicativo": "CM8SS",
      "nombre": "JOSE LUIS",
      "dist": 1424,
      "grilla": "EL92ET"
    },
    "zonaActiva": [
      "EK70",
      7
    ],
    "timestamp": "2026-05-22T23:34:28.891Z"
  },
  {
    "fecha": "22/5/2026",
    "emision": "7833",
    "revista": "Revista Matutina",
    "operador": "TI2OX",
    "nombreOp": "Carlos Castillo",
    "totalEstaciones": 40,
    "duracion": "2h 14min",
    "tempProm": "22.2",
    "masLejano": {
      "indicativo": "TI3JKS",
      "nombre": "Juan Carlos",
      "dist": 228,
      "grilla": "EJ89XV"
    },
    "zonaActiva": [
      "EJ79",
      13
    ],
    "timestamp": "2026-05-22T14:48:46.097Z"
  },
  {
    "fecha": "21/5/2026",
    "emision": "009636",
    "revista": "RUEDA DE ORO_TI5RHB_HORA UTC:22 A 23:15_FRECUENCIA 7130 MHZ",
    "operador": "TI2GC",
    "nombreOp": "GUILLERMO",
    "totalEstaciones": 17,
    "duracion": "55min 16s",
    "tempProm": "21.4",
    "masLejano": {
      "indicativo": "CM8SS",
      "nombre": "JOSE LUIS",
      "dist": 1424,
      "grilla": "EL92ET"
    },
    "zonaActiva": [
      "EK70",
      8
    ],
    "timestamp": "2026-05-21T23:09:21.365Z"
  }
]